<?xml version="1.0" encoding="UTF-8"?>
<dataset>
<PetGrow id="1001" HEALTH="0" HENGER="5" CLEAN="5" APPEASE="5" GROW="0" GROWUP="50" />
<PetGrow id="1002" HEALTH="0" HENGER="5" CLEAN="5" APPEASE="5" GROW="0" GROWUP="100" />
<PetGrow id="1003" HEALTH="0" HENGER="5" CLEAN="5" APPEASE="5" GROW="0" GROWUP="0" />
<PetGrow id="1011" HEALTH="0" HENGER="5" CLEAN="5" APPEASE="5" GROW="0" GROWUP="50" />
<PetGrow id="1012" HEALTH="0" HENGER="5" CLEAN="5" APPEASE="5" GROW="0" GROWUP="100" />
<PetGrow id="1013" HEALTH="0" HENGER="5" CLEAN="5" APPEASE="5" GROW="0" GROWUP="0" />
<PetGrow id="1021" HEALTH="0" HENGER="5" CLEAN="5" APPEASE="5" GROW="0" GROWUP="50" />
<PetGrow id="1022" HEALTH="0" HENGER="5" CLEAN="5" APPEASE="5" GROW="0" GROWUP="100" />
<PetGrow id="1023" HEALTH="0" HENGER="5" CLEAN="5" APPEASE="5" GROW="0" GROWUP="0" />
<PetGrow id="1031" HEALTH="0" HENGER="5" CLEAN="5" APPEASE="5" GROW="0" GROWUP="50" />
<PetGrow id="1032" HEALTH="0" HENGER="5" CLEAN="5" APPEASE="5" GROW="0" GROWUP="100" />
<PetGrow id="1033" HEALTH="0" HENGER="5" CLEAN="5" APPEASE="5" GROW="0" GROWUP="0" />
</dataset>